flake8_all_not_strings.py
flake8_all_not_strings-0.0.3.dist-info/licenses/LICENSE
flake8_all_not_strings-0.0.3.dist-info/METADATA
flake8_all_not_strings-0.0.3.dist-info/WHEEL
flake8_all_not_strings-0.0.3.dist-info/entry_points.txt
flake8_all_not_strings-0.0.3.dist-info/top_level.txt
flake8_all_not_strings-0.0.3.dist-info/RECORD
