Metadata-Version: 2.4
Name: flake8_all_not_strings
Version: 0.0.3
Summary: flake8 plugin which checks that modules under `__all__` are defined as strings
Home-page: https://github.com/ggupta2005/flake8-all-not-strings
Author: Gaurav Gupta
Author-email: ggupta2005@gmail.com
License: MIT
Classifier: License :: OSI Approved :: MIT License
Classifier: Programming Language :: Python :: 3 :: Only
Classifier: Programming Language :: Python :: 3.8
Classifier: Programming Language :: Python :: 3.9
Classifier: Programming Language :: Python :: 3.10
Classifier: Programming Language :: Python :: 3.11
Classifier: Programming Language :: Python :: 3.12
Classifier: Programming Language :: Python :: 3.13
Classifier: Programming Language :: Python :: Implementation :: CPython
Classifier: Operating System :: OS Independent
Classifier: Development Status :: 3 - Alpha
License-File: LICENSE
Requires-Dist: flake8>=3
Dynamic: license-file
